modul/__init__.py
modul/arif.py
modul/draw.py
little_json-0.0.1.dist-info/METADATA
little_json-0.0.1.dist-info/WHEEL
little_json-0.0.1.dist-info/top_level.txt
little_json-0.0.1.dist-info/RECORD
