Metadata-Version: 2.4
Name: little_json
Version: 0.0.1
Summary: Drawing operations and json
Author: Jasurbek
Author-email: olimjonovzilxa@gmail.com
Requires: ujson
Requires-Python: >=3.6
Dynamic: author
Dynamic: author-email
Dynamic: description
Dynamic: description-content-type
Dynamic: requires
Dynamic: requires-python
Dynamic: summary
